[
 {
   "name": "POSTECH C5",
   "type": "building",
   "lon": 129.3257761001587,
   "lat": 36.01432427345841
 },
 {
   "name": "POSTECH road",
   "type": "road",
   "lon": 129.32618379592896,
   "lat": 36.0129183870397
 },
 {
   "name": "POSTECH dorm 21",
   "type": "building",
   "lon": 129.32070136070251,
   "lat": 36.01707522557408
 },
 {
   "name": "POSTECH dorm 20",
   "type": "building",
   "lon": 129.32080328464508,
   "lat": 36.0164894630592
 },
 {
   "name": "POSTECH dorm 20",
   "type": "building",
   "lon": 129.32080328464508,
   "lat": 36.0164894630592
 },
 {
   "name": "POSTECH dorm 20",
   "type": "building",
   "lon": 129.32080328464508,
   "lat": 36.0164894630592
 },
 {
   "name": "POSTECH dorm 1",
   "type": "building",
   "lon": 129.3197625875473,
   "lat": 36.016402683057116
 },
 {
   "name": "POSTECH dorm 3",
   "type": "building",
   "lon": 129.32023465633392,
   "lat": 36.016124986408286
 },
 {
   "name": "POSTECH dorm 2",
   "type": "building",
   "lon": 129.31945681571958,
   "lat": 36.01625949584475
 },
 {
   "name": "POSTECH dorm 4",
   "type": "building",
   "lon": 129.31993961334229,
   "lat": 36.01598179869141
 },
 {
   "name": "POSTECH dorm 6",
   "type": "building",
   "lon": 129.32050824165344,
   "lat": 36.01549148726615
 },
 {
   "name": "POSTECH dorm 5",
   "type": "building",
   "lon": 129.32076573371887,
   "lat": 36.01582993264682
 },
 {
   "name": "POSTECH dorm 8",
   "type": "building",
   "lon": 129.3210393190384,
   "lat": 36.015304907780994
 },
 {
   "name": "POSTECH dorm 7",
   "type": "building",
   "lon": 129.32128071784973,
   "lat": 36.01555223397994
 },
 {
   "name": "POSTECH dorm 9",
   "type": "building",
   "lon": 129.3213826417923,
   "lat": 36.015925391337575
 },
 {
   "name": "POSTECH dorm 11",
   "type": "building",
   "lon": 129.3213826417923,
   "lat": 36.01638966604855
 },
 {
   "name": "POSTECH dorm 19",
   "type": "building",
   "lon": 129.32140946388245,
   "lat": 36.01680620925598
 },
 {
   "name": "POSTECH dorm 17",
   "type": "building",
   "lon": 129.32182252407074,
   "lat": 36.016927700610125
 },
 {
   "name": "POSTECH dorm 12",
   "type": "building",
   "lon": 129.32182252407074,
   "lat": 36.01652851402899
 },
 {
   "name": "POSTECH dorm 10",
   "type": "building",
   "lon": 129.32175278663632,
   "lat": 36.01606857915694
 },
 {
   "name": "POSTECH dorm 13",
   "type": "building",
   "lon": 129.32234823703766,
   "lat": 36.01673244655675
 },
 {
   "name": "POSTECH dorm 16",
   "type": "building",
   "lon": 129.3220853805542,
   "lat": 36.0171272931425
 },
 {
   "name": "POSTECH dorm 18",
   "type": "building",
   "lon": 129.32210683822632,
   "lat": 36.01759156077328
 },
 {
   "name": "POSTECH dorm 15",
   "type": "building",
   "lon": 129.32251989841458,
   "lat": 36.01724444504565
 },
 {
   "name": "POSTECH dorm 14",
   "type": "building",
   "lon": 129.32272374629974,
   "lat": 36.01683224313337
 },
 {
   "name": "POSTECH dorm 2",
   "type": "building",
   "lon": 129.32300806045532,
   "lat": 36.01649380205681
 },
 {
   "name": "POSTECH dorm 3",
   "type": "building",
   "lon": 129.32346940040588,
   "lat": 36.01649814105416
 },
 {
   "name": "POSTECH dorm 1",
   "type": "building",
   "lon": 129.32326555252075,
   "lat": 36.01611630837224
 },
 {
   "name": "POSTECH cafeteria",
   "type": "building",
   "lon": 129.32241797447205,
   "lat": 36.015643353962886
 },
 {
   "name": "POSTECH road",
   "type": "road",
   "lon": 129.31979477405548,
   "lat": 36.01621610572904
 },
 {
   "name": "POSTECH road",
   "type": "road",
   "lon": 129.32028830051422,
   "lat": 36.01591671327957
 },
 {
   "name": "POSTECH road",
   "type": "road",
   "lon": 129.3204814195633,
   "lat": 36.01580389843837
 },
 {
   "name": "POSTECH road",
   "type": "road",
   "lon": 129.3208086490631,
   "lat": 36.01558694636682
 },
 {
   "name": "POSTECH road",
   "type": "road",
   "lon": 129.32151675224304,
   "lat": 36.01527019526992
 },
 {
   "name": "POSTECH road",
   "type": "road",
   "lon": 129.32177424430847,
   "lat": 36.015179074855595
 },
 {
   "name": "POSTECH road",
   "type": "road",
   "lon": 129.32200491428375,
   "lat": 36.014884017552994
 },
 {
   "name": "POSTECH pond",
   "type": "river",
   "lon": 129.32229459285736,
   "lat": 36.015153040432146
 },
 {
   "name": "POSTECH pond",
   "type": "river",
   "lon": 129.32277739048004,
   "lat": 36.01504890265237
 },
 {
   "name": "POSTECH road",
   "type": "road",
   "lon": 129.32270765304565,
   "lat": 36.01470177572608
 },
 {
   "name": "POSTECH forest",
   "type": "mountain",
   "lon": 129.3223750591278,
   "lat": 36.01490571298052
 },
 {
   "name": "POSTECH forest",
   "type": "mountain",
   "lon": 129.32259500026703,
   "lat": 36.015356976518966
 },
 {
   "name": "POSTECH road",
   "type": "road",
   "lon": 129.32309925556183,
   "lat": 36.01483628759144
 },
 {
   "name": "POSTECH road",
   "type": "road",
   "lon": 129.32323336601257,
   "lat": 36.01515737950331
 },
 {
   "name": "POSTECH road",
   "type": "road",
   "lon": 129.32295441627502,
   "lat": 36.01540904522254
 },
 {
   "name": "POSTECH road",
   "type": "road",
   "lon": 129.32292759418488,
   "lat": 36.015816915543674
 },
 {
   "name": "POSTECH road",
   "type": "road",
   "lon": 129.32259500026703,
   "lat": 36.0159514255059
 },
 {
   "name": "POSTECH road",
   "type": "road",
   "lon": 129.3221390247345,
   "lat": 36.01588634006897
 },
 {
   "name": "POSTECH road",
   "type": "road",
   "lon": 129.3224662542343,
   "lat": 36.01616403755866
 },
 {
   "name": "POSTECH road",
   "type": "road",
   "lon": 129.32220339775085,
   "lat": 36.01612932542594
 },
 {
   "name": "POSTECH road",
   "type": "road",
   "lon": 129.32263791561127,
   "lat": 36.016407022059504
 },
 {
   "name": "POSTECH road",
   "type": "road",
   "lon": 129.32303488254547,
   "lat": 36.016298546928454
 },
 {
   "name": "POSTECH road",
   "type": "road",
   "lon": 129.3226593732834,
   "lat": 36.01625081782354
 },
 {
   "name": "POSTECH road",
   "type": "road",
   "lon": 129.32329773902893,
   "lat": 36.01638532704522
 },
 {
   "name": "POSTECH road",
   "type": "road",
   "lon": 129.32159185409543,
   "lat": 36.01719671651353
 },
 {
   "name": "POSTECH road",
   "type": "road",
   "lon": 129.32181179523468,
   "lat": 36.01752213775008
 },
 {
   "name": "POSTECH road",
   "type": "road",
   "lon": 129.32186543941498,
   "lat": 36.01555223397994
 },
 {
   "name": "POSTECH road",
   "type": "road",
   "lon": 129.32160794734955,
   "lat": 36.01578220325809
 },
 {
   "name": "POSTECH road",
   "type": "road",
   "lon": 129.32157039642334,
   "lat": 36.016207427703044
 },
 {
   "name": "POSTECH road",
   "type": "road",
   "lon": 129.32065844535828,
   "lat": 36.01676281944128
 },
 {
   "name": "POSTECH road",
   "type": "road",
   "lon": 129.32059943675995,
   "lat": 36.016207427703044
 },
 {
   "name": "POSTECH road",
   "type": "road",
   "lon": 129.32044386863708,
   "lat": 36.01727047877825
 },
 {
   "name": "POSTECH road",
   "type": "road",
   "lon": 129.32145774364471,
   "lat": 36.017838879796514
 },
 {
   "name": "POSTECH road",
   "type": "road",
   "lon": 129.32182252407074,
   "lat": 36.01796036955875
 },
 {
   "name": "POSTECH road",
   "type": "road",
   "lon": 129.32393074035642,
   "lat": 36.01505324172926
 },
 {
   "name": "POSTECH road",
   "type": "road",
   "lon": 129.32360887527463,
   "lat": 36.01448915972874
 },
 {
   "name": "POSTECH road",
   "type": "road",
   "lon": 129.32479977607727,
   "lat": 36.01566938822435
 },
 {
   "name": "POSTECH posville3",
   "type": "building",
   "lon": 129.32525038719177,
   "lat": 36.01681488721608
 },
 {
   "name": "POSTECH posville 2",
   "type": "building",
   "lon": 129.3251645565033,
   "lat": 36.016233461778185
 },
 {
   "name": "POSTECH posville4",
   "type": "building",
   "lon": 129.325829744339,
   "lat": 36.0163983440545
 },
 {
   "name": "POSTECH posville 5",
   "type": "building",
   "lon": 129.3262481689453,
   "lat": 36.015339620276805
 },
 {
   "name": "POSTECH road",
   "type": "road",
   "lon": 129.32530403137207,
   "lat": 36.01591237425021
 },
 {
   "name": "POSTECH road",
   "type": "road",
   "lon": 129.325829744339,
   "lat": 36.01611196935387
 },
 {
   "name": "POSTECH road",
   "type": "road",
   "lon": 129.323490858078,
   "lat": 36.01390771713374
 },
 {
   "name": "POSTECH road",
   "type": "road",
   "lon": 129.32358741760254,
   "lat": 36.0134477669679
 },
 {
   "name": "POSTECH road",
   "type": "road",
   "lon": 129.3238878250122,
   "lat": 36.01280556790689
 },
 {
   "name": "POSTECH road",
   "type": "road",
   "lon": 129.32424187660217,
   "lat": 36.01203318642994
 },
 {
   "name": "POSTECH posville 6",
   "type": "building",
   "lon": 129.32493925094604,
   "lat": 36.014003178152585
 },
 {
   "name": "POSTECH road",
   "type": "road",
   "lon": 129.32505726814267,
   "lat": 36.01506191988238
 },
 {
   "name": "POSTECH road",
   "type": "road",
   "lon": 129.32530403137207,
   "lat": 36.01446312507741
 },
 {
   "name": "POSTECH road",
   "type": "road",
   "lon": 129.3257224559784,
   "lat": 36.01370811644802
 },
 {
   "name": "POSTECH library",
   "type": "building",
   "lon": 129.32519674301147,
   "lat": 36.01279688950536
 },
 {
   "name": "POSTECH road",
   "type": "road",
   "lon": 129.32644128799438,
   "lat": 36.012423717336105
 },
 {
   "name": "POSTECH road",
   "type": "road",
   "lon": 129.32670950889585,
   "lat": 36.01198111549627
 },
 {
   "name": "POSTECH road",
   "type": "road",
   "lon": 129.32698845863342,
   "lat": 36.01138229728672
 },
 {
   "name": "POSTECH road",
   "type": "road",
   "lon": 129.3253469467163,
   "lat": 36.011920366030175
 },
 {
   "name": "POSTECH road",
   "type": "road",
   "lon": 129.32622671127316,
   "lat": 36.01069668824374
 },
 {
   "name": "POSTECH road",
   "type": "road",
   "lon": 129.32682752609253,
   "lat": 36.010904975165865
 },
 {
   "name": "POSTECH road",
   "type": "road",
   "lon": 129.32721376419067,
   "lat": 36.011069868588926
 },
 {
   "name": "POSTECH road",
   "type": "road",
   "lon": 129.32471930980682,
   "lat": 36.016207427703044
 },
 {
   "name": "POSTECH road",
   "type": "road",
   "lon": 129.32477295398712,
   "lat": 36.01662831086382
 },
 {
   "name": "POSTECH road",
   "type": "road",
   "lon": 129.32481050491333,
   "lat": 36.01715766587485
 },
 {
   "name": "POSTECH road",
   "type": "road",
   "lon": 129.3248748779297,
   "lat": 36.01759156077328
 },
 {
   "name": "POSTECH road",
   "type": "road",
   "lon": 129.32489097118378,
   "lat": 36.01802979219591
 },
 {
   "name": "POSTECH road",
   "type": "road",
   "lon": 129.32492315769196,
   "lat": 36.018650254300006
 },
 {
   "name": "POSTECH road",
   "type": "road",
   "lon": 129.3249499797821,
   "lat": 36.01915790147896
 },
 {
   "name": "POSTECH GYM",
   "type": "building",
   "lon": 129.32434380054474,
   "lat": 36.01918393457948
 },
 {
   "name": "POSTECH GYM",
   "type": "building",
   "lon": 129.3239414691925,
   "lat": 36.019001702695284
 },
 {
   "name": "POSTECH road",
   "type": "road",
   "lon": 129.32489097118378,
   "lat": 36.01838558225165
 },
 {
   "name": "POSTECH road",
   "type": "road",
   "lon": 129.32498216629028,
   "lat": 36.01978269351776
 },
 {
   "name": "POSTECH student union",
   "type": "building",
   "lon": 129.32071208953857,
   "lat": 36.01279688950536
 },
 {
   "name": "POSTECH cafteria",
   "type": "building",
   "lon": 129.32101249694824,
   "lat": 36.01301818844565
 },
 {
   "name": "POSTECH road",
   "type": "road",
   "lon": 129.32049214839935,
   "lat": 36.01316572072735
 },
 {
   "name": "POSTECH road",
   "type": "road",
   "lon": 129.32094275951385,
   "lat": 36.01347380195462
 },
 {
   "name": "POSTECH road",
   "type": "road",
   "lon": 129.32145774364471,
   "lat": 36.01359529844556
 },
 {
   "name": "POSTECH road",
   "type": "road",
   "lon": 129.32179570198056,
   "lat": 36.013300235214125
 },
 {
   "name": "POSTECH road",
   "type": "road",
   "lon": 129.3221229314804,
   "lat": 36.01293574381503
 },
 {
   "name": "POSTECH road",
   "type": "road",
   "lon": 129.32254672050476,
   "lat": 36.01251050171917
 },
 {
   "name": "POSTECH road",
   "type": "road",
   "lon": 129.32284712791443,
   "lat": 36.012310897495304
 },
 {
   "name": "POSTECH road",
   "type": "road",
   "lon": 129.3234050273895,
   "lat": 36.01268407019866
 },
 {
   "name": "POSTECH road",
   "type": "road",
   "lon": 129.3275088071823,
   "lat": 36.010579526608176
 },
 {
   "name": "POSTECH road",
   "type": "road",
   "lon": 129.3277233839035,
   "lat": 36.01016728983959
 },
 {
   "name": "Songdo beach",
   "type": "ocean",
   "lon": 129.38332557678223,
   "lat": 36.0384807732436
 },
 {
   "name": "Songdo beach",
   "type": "ocean",
   "lon": 129.37980651855466,
   "lat": 36.04375534519075
 },
 {
   "name": "Songdo baech",
   "type": "ocean",
   "lon": 129.37808990478516,
   "lat": 36.049515329329886
 },
 {
   "name": "Yeongil-dae",
   "type": "ocean",
   "lon": 129.3826389312744,
   "lat": 36.053540128339755
 },
 {
   "name": "Yeongil-dae",
   "type": "ocean",
   "lon": 129.38332557678223,
   "lat": 36.05867491793256
 },
 {
   "name": "Yeongil-dae",
   "type": "ocean",
   "lon": 129.3907928466797,
   "lat": 36.06096464851829
 },
 {
   "name": "Songdo beach",
   "type": "ocean",
   "lon": 129.38358306884766,
   "lat": 36.033622302299555
 },
 {
   "name": "POSTECH road",
   "type": "road",
   "lon": 129.32539522647858,
   "lat": 36.015500165371
 },
 {
   "name": "Hyeongsan-gang",
   "type": "river",
   "lon": 129.3818235397339,
   "lat": 36.02640344919376
 },
 {
   "name": "Hyeongsan-gang",
   "type": "river",
   "lon": 129.37718868255612,
   "lat": 36.01793433605402
 },
 {
   "name": "Hyeongsan-gang",
   "type": "river",
   "lon": 129.3674898147583,
   "lat": 36.00672177401952
 },
 {
   "name": "Hyeongsan-gang",
   "type": "river",
   "lon": 129.35813426971433,
   "lat": 36.002347400987304
 },
 {
   "name": "Hyeongsan-gang",
   "type": "river",
   "lon": 129.34611797332764,
   "lat": 36.00220852802778
 },
 {
   "name": "Hyeongsan-gang",
   "type": "river",
   "lon": 129.3244457244873,
   "lat": 36.00255570996805
 },
 {
   "name": "Hyeongsan-gang",
   "type": "river",
   "lon": 129.3134593963623,
   "lat": 35.99873662455378
 },
 {
   "name": "Hyeongsan-gang",
   "type": "river",
   "lon": 129.33388710021973,
   "lat": 36.00300704420516
 },
 {
   "name": "POSTECH road",
   "type": "road",
   "lon": 129.32570099830625,
   "lat": 36.011226083092616
 },
 {
   "name": "POSTECH road",
   "type": "road",
   "lon": 129.32251453399658,
   "lat": 36.01684959904684
 },
 {
   "name": "POSTECH road",
   "type": "road",
   "lon": 129.32245016098022,
   "lat": 36.01710125936259
 },
 {
   "name": "POSTECH road",
   "type": "road",
   "lon": 129.32232677936554,
   "lat": 36.017027496939505
 },
 {
   "name": "POSTECH road",
   "type": "road",
   "lon": 129.32222485542297,
   "lat": 36.01731386831347
 },
 {
   "name": "POSTECH road",
   "type": "road",
   "lon": 129.32158648967743,
   "lat": 36.01665000581119
 },
 {
   "name": "POSTECH road",
   "type": "road",
   "lon": 129.32158648967743,
   "lat": 36.01704485280998
 }
]
